{
    "0": [
        [
            "ano",
            0.10113843099412455
        ],
        [
            "data",
            0.07930991371903473
        ],
        [
            "idade",
            0.057296398777837154
        ],
        [
            "publico",
            0.05151994364158152
        ],
        [
            "contribuicao",
            0.0500365354431023
        ],
        [
            "informar",
            0.03143940262125204
        ],
        [
            "aparecer",
            0.030881509803482247
        ],
        [
            "dado",
            0.03075470299716524
        ],
        [
            "informacao",
            0.030085116250935955
        ],
        [
            "requisito",
            0.027787964685929457
        ]
    ],
    "1": [
        [
            "facil",
            0.1612448641304794
        ],
        [
            "ferramenta",
            0.09369767688772787
        ],
        [
            "ferramentar",
            0.06468615169270353
        ],
        [
            "linguagem",
            0.05649655555303872
        ],
        [
            "claro",
            0.05605924388650066
        ],
        [
            "acrescentar",
            0.056022964495906886
        ],
        [
            "utilizar",
            0.05396753699507471
        ],
        [
            "intuitivo",
            0.04842530677274572
        ],
        [
            "simples",
            0.047321457559903884
        ],
        [
            "tecnico",
            0.04506030138397981
        ]
    ],
    "2": [
        [
            "iniciativa",
            0.11779318227767872
        ],
        [
            "excelente",
            0.09147739804873815
        ],
        [
            "parabens",
            0.06927558842245608
        ],
        [
            "futuro",
            0.050334363731644675
        ],
        [
            "gostar",
            0.047327819096287846
        ],
        [
            "ferramenta",
            0.0465095432350783
        ],
        [
            "ajudar",
            0.04573997480515408
        ],
        [
            "vida",
            0.044741656650350826
        ],
        [
            "facilitar",
            0.044741656650350826
        ],
        [
            "contribuicao",
            0.04400116399819354
        ]
    ],
    "3": [
        [
            "publico",
            0.13049885431695074
        ],
        [
            "federal",
            0.07884715341216589
        ],
        [
            "privado",
            0.06836362165978764
        ],
        [
            "ano",
            0.06003110281530769
        ],
        [
            "inss",
            0.05742039853310297
        ],
        [
            "trabalhar",
            0.053242563585436754
        ],
        [
            "contribuicao",
            0.050025196681990076
        ],
        [
            "trabalho",
            0.046208135399485345
        ],
        [
            "outro",
            0.04277157287272306
        ],
        [
            "anterior",
            0.03966495357417183
        ]
    ],
    "4": [
        [
            "opcao",
            0.07650268627481852
        ],
        [
            "legal",
            0.0480626699932776
        ],
        [
            "regra",
            0.03847372120706213
        ],
        [
            "deficiencia",
            0.03715950264825801
        ],
        [
            "duvida",
            0.032818527556495745
        ],
        [
            "faltar",
            0.03255348110647492
        ],
        [
            "fundamento",
            0.028824419795862286
        ],
        [
            "lei",
            0.02833510431362985
        ],
        [
            "direito",
            0.02792645079870069
        ],
        [
            "especial",
            0.02441037234328035
        ]
    ],
    "5": [
        [
            "rgp",
            0.1745429147953807
        ],
        [
            "ctc",
            0.13979257975305476
        ],
        [
            "periodo",
            0.12341552376327762
        ],
        [
            "pcd",
            0.089264058236504
        ],
        [
            "incluir",
            0.08221411956524013
        ],
        [
            "rpps",
            0.0794001690305288
        ],
        [
            "campo",
            0.060221602341937394
        ],
        [
            "permitir",
            0.060033550538940605
        ],
        [
            "inclusao",
            0.05947408250290483
        ],
        [
            "rgps",
            0.05573932080746346
        ]
    ],
    "6": [
        [
            "gostar",
            0.14149835472285419
        ],
        [
            "util",
            0.07642349360818015
        ],
        [
            "conseguir",
            0.07390534014642883
        ],
        [
            "comentario",
            0.07132258058261047
        ],
        [
            "sugestao",
            0.06292212262632921
        ],
        [
            "parabens",
            0.06273246249802567
        ],
        [
            "situacao",
            0.05841242490474453
        ],
        [
            "funcionar",
            0.05596015848189803
        ],
        [
            "entendi",
            0.04993647614858653
        ],
        [
            "declarar",
            0.04617331566699051
        ]
    ],
    "7": [
        [
            "salario",
            0.10232333623120546
        ],
        [
            "remuneracao",
            0.07727050462046224
        ],
        [
            "desconto",
            0.05018472222003195
        ],
        [
            "renda",
            0.049492259461956525
        ],
        [
            "liquido",
            0.03943085317288225
        ],
        [
            "aparecer",
            0.03754527808181553
        ],
        [
            "receber",
            0.03645990946387667
        ],
        [
            "contribuicao",
            0.03359999324172159
        ],
        [
            "beneficio",
            0.0328736557461844
        ],
        [
            "faltar",
            0.03285211832158859
        ]
    ],
    "8": [
        [
            "migrar",
            0.22820147483412215
        ],
        [
            "rpc",
            0.18037863539081925
        ],
        [
            "migracao",
            0.17978011070627678
        ],
        [
            "beneficio",
            0.16313551664044007
        ],
        [
            "especial",
            0.14407770231688943
        ],
        [
            "regime",
            0.10538021989715964
        ],
        [
            "calculo",
            0.09191841243942596
        ],
        [
            "visao",
            0.07131809692469078
        ],
        [
            "financeiro",
            0.054910021348023
        ],
        [
            "situacao",
            0.054274878140658456
        ]
    ],
    "9": [
        [
            "informacao",
            0.05899580062070898
        ],
        [
            "calculo",
            0.04425994064151208
        ],
        [
            "ferramenta",
            0.03948112343837579
        ],
        [
            "aplicativo",
            0.03280188527063197
        ],
        [
            "resultado",
            0.031133930491700473
        ],
        [
            "opcao",
            0.02900418210716301
        ],
        [
            "facil",
            0.02588315789776569
        ],
        [
            "duvida",
            0.024856295625850133
        ],
        [
            "precisar",
            0.021791353961997106
        ],
        [
            "parabens",
            0.021384295996269762
        ]
    ]
}